pystreed.libs/libstdc++-8baf04f9.so.6.0.28
pystreed.libs/libgcc_s-8b50eaaa.so.1
pystreed-1.3.7.dist-info/METADATA
pystreed-1.3.7.dist-info/LICENSE
pystreed-1.3.7.dist-info/top_level.txt
pystreed-1.3.7.dist-info/WHEEL
pystreed-1.3.7.dist-info/RECORD
pystreed/base.py
pystreed/utils.py
pystreed/cstreed.cpython-311-i386-linux-musl.so
pystreed/classification.py
pystreed/instance_cost_sensitive_classification.py
pystreed/__init__.py
pystreed/data.py
pystreed/group_fair.py
pystreed/prescriptive_policy_generation.py
pystreed/survival_analysis.py
pystreed/binarizer.py
pystreed/cost_sensitive_classification.py
pystreed/regression.py
