Metadata-Version: 2.1
Name: pystreed
Version: 1.3.7
Summary: Python Implementation of STreeD: Dynamic Programming Approach for Optimal Decision Trees with Separable objectives and Constraints
Author-email: "Jacobus G. M. van der Linden" <J.G.M.vanderLinden@tudelft.nl>, Emir Demirović <E.Demirovic@tudelft.nl>, "Mathijs M. de Weerdt" <M.M.deWeerdt@tudelft.nl>
Maintainer-email: "Jacobus G. M. van der Linden" <J.G.M.vanderLinden@tudelft.nl>
License: Copyright 2023 Jacobus G. M. van der Linden, Delft University of Technology
Project-URL: Repository, https://github.com/AlgTUDelft/pystreed
Classifier: Programming Language :: Python :: 3
Classifier: License :: OSI Approved :: MIT License
Classifier: Operating System :: OS Independent
Requires-Python: >=3.8
License-File: LICENSE
Requires-Dist: pandas >=1.0.0
Requires-Dist: numpy >=1.18.0
Requires-Dist: scikit-learn >=1.2.0
Requires-Dist: scikit-survival
Requires-Dist: typing-extensions
Provides-Extra: dev
Requires-Dist: pytest >=5.3.0 ; extra == 'dev'
Requires-Dist: pytest-cov >=2.8.0 ; extra == 'dev'
